{
  "sources": [
    {
      "title": "【Re:AcT /リアクト】公式チャンネル",
      "feedUrl": "https://www.youtube.com/feeds/videos.xml?channel_id=UC90vyzmRgWCE17-uWNsKW2Q",
      "siteUrl": "https://www.youtube.com/channel/UC90vyzmRgWCE17-uWNsKW2Q",
      "articles": [
        {
          "id": "https://www.youtube.com/watch?v=uBBB1LKiRj8",
          "author": null,
          "description": "",
          "link": "https://www.youtube.com/watch?v=uBBB1LKiRj8",
          "publishedOn": "2024-01-18T13:20:38.000Z",
          "wordCount": null,
          "title": "2023.12.30 Re:AcT LIVE 「ユメニミタカラ ~ MAGICAL HARMONY ~」",
          "imageUrl": null
        },
        {
          "id": "https://www.youtube.com/watch?v=d-40TQp9t9s",
          "author": null,
          "description": "",
          "link": "https://www.youtube.com/watch?v=d-40TQp9t9s",
          "publishedOn": "2024-01-06T12:53:29.000Z",
          "wordCount": null,
          "title": "【 #ユメニミタカラ】一緒に観よう❗年末ライブアーカイブ同時視聴新年会 【リアクト／Re:AcT】",
          "imageUrl": null
        }
      ]
    }
  ],
  "cliVersion": "1.15.1"
}